app.py
rmnt/__init__.py
rmnt/__main__.py
rmnt/app.py
rmnt/exec.py
rmnt/generator.py
rmnt/orchestrator.py
rmnt/utils.py
rmnt-1.0.4.dist-info/LICENSE
rmnt-1.0.4.dist-info/METADATA
rmnt-1.0.4.dist-info/WHEEL
rmnt-1.0.4.dist-info/entry_points.txt
rmnt-1.0.4.dist-info/top_level.txt
rmnt-1.0.4.dist-info/RECORD
